{"gtm_id": "", "ga4_id": "", "ua_id": "", "gads_id": "", "has_google_ads": false, "fb_pixel_id": "", "has_facebook_pixel": false, "has_whatsapp": false, "whatsapp_number": "", "cms": "wordpress", "booking_system": "", "chat_widget": "", "analytics_tools": [], "payment_tools": ["stripe"], "found_emails": [], "found_phones": ["7032645540", "1766871380", "1772627757", "7020045540", "1750536758"], "social_links": {}, "has_lead_form": true, "has_click_to_call": true, "_cached_at": "2026-03-04T18:05:58.070909"}